{
    "1995": [
        "CIV",
        "Deftones",
        "Face to Face",
        "Fluf",
        "L7",
        "No Doubt",
        "No Use for a Name",
        "Orange 9mm",
        "Quicksand",
        "Seaweed",
        "Sick of It All",
        "Sublime",
        "Supernova",
        "Swingin' Utters",
        "Tilt",
        "Wizo"
    ],
    "1996": [
        "Beck",
        "Blink-182",
        "CIV",
        "Dance Hall Crashers",
        "Deftones",
        "Dick Dale",
        "Down by Law",
        "Face to Face",
        "The Figgs",
        "Fishbone",
        "Fluf",
        "The Mighty Mighty Bosstones",
        "Mushroomhead",
        "NOFX",
        "Pennywise",
        "Red Five",
        "Rocket from the Crypt",
        "Suicide Machines",
        "Unwritten Law"
    ],
    "1997": [
        "Bad Religion",
        "Blink-182",
        "Descendents",
        "Hed PE",
        "Jimmy 2 Times",
        "Lagwagon",
        "Latex Generation",
        "Less Than Jake",
        "Limp Bizkit",
        "The Mighty Mighty Bosstones",
        "Millencolin",
        "Murder City Devils",
        "Orange 9mm",
        "Pennywise",
        "Reel Big Fish",
        "Sick of It All",
        "Snot",
        "Social Distortion",
        "Strung Out",
        "Sugar Ray",
        "Trading Bryson",
        "Vision of Disorder",
        "White Kaps"
    ],
    "1998": [
        "Amazing Royal Crowns",
        "The Aquabats",
        "Atomic Fireballs",
        "Bad Religion",
        "Cherry Poppin' Daddies",
        "CIV",
        "Deftones",
        "Die Toten Hosen",
        "Fu Manchu",
        "The Get Up Kids",
        "Godsmack",
        "Hatebreed",
        "Hepcat",
        "Home Grown",
        "H2O",
        "Incubus",
        "Indofin",
        "Kid Rock",
        "Latex Generation",
        "L.E.S. Stitches",
        "Mad Caddies",
        "MxPx",
        "NOFX",
        "No Use for a Name",
        "Pietasters",
        "Rancid",
        "Reverend Horton Heat",
        "Royal Crown Revue",
        "Save Ferris",
        "Skavoovie and the Epitones",
        "The Smooths",
        "Snapcase",
        "The Specials",
        "Staind",
        "Swingin' Utters",
        "Tilt",
        "Unsane",
        "Unwritten Law",
        "The Urge",
        "The Vandals",
        "Zebrahead"
    ],
    "1999": [
        "Anthrophobia",
        "Anti-Flag",
        "The Black Eyed Peas",
        "Blink-182",
        "Bombay Cowtippers",
        "Bouncing Souls",
        "Buck-O-Nine",
        "CKY",
        "Dropkick Murphys",
        "Eminem",
        "H2O",
        "Ice-T",
        "Jacky Jasper",
        "Less Than Jake",
        "The Living End",
        "Molotov",
        "Pennywise",
        "Sevendust",
        "Simple Plan",
        "Spring Heeled Jack",
        "Suicidal Tendencies",
        "Unwritten Law",
        "The Vandals",
        "Vision of Disorder"
    ],
    "2000": [
        "A.N.I.M.A.L.",
        "Anti-Flag",
        "Avail",
        "Beatsteaks",
        "Bif Naked",
        "CKY",
        "Deviates",
        "Flogging Molly",
        "Gob",
        "Good Riddance",
        "Green Day",
        "Hepcat",
        "The Know How[29]",
        "Kottonmouth Kings",
        "Long Beach Dub All-Stars",
        "Luckie Strike",
        "Lunachicks",
        "The Mighty Mighty Bosstones",
        "Millencolin",
        "Morgan Heritage",
        "The Muffs",
        "MxPx",
        "No Doubt",
        "NOFX",
        "One Minute Silence",
        "Papa Roach",
        "Save Ferris",
        "Saves the Day",
        "Simple Plan",
        "Six Feet Under",
        "Skarhead",
        "Snapcase",
        "The Stingrays",
        "Suicide Machines",
        "Weezer"
    ],
    "2001": [
        "The Ataris",
        "Blink-182",
        "Bouncing Souls",
        "D12",
        "Deviates",
        "Dropkick Murphys",
        "Esham",
        "Fear",
        "Fenix TX",
        "Flogging Molly",
        "Good Charlotte",
        "H2O",
        "Jacky Jasper",
        "The Juliana Theory",
        "Jurassic 5",
        "The Know How[29]",
        "Kool Keith",
        "Less Than Jake",
        "The Living End",
        "Long Beach Dub All-Stars",
        "Luckie Strike",
        "Madcap",
        "Me First and the Gimme Gimmes",
        "Midtown",
        "The Misfits",
        "New Found Glory",
        "Obtik",
        "Pennywise",
        "Rancid",
        "Rollins Band",
        "Simple Plan",
        "Sprout",
        "Sugarcult",
        "Sum 41",
        "Switched",
        "Thrice",
        "The Vandals"
    ],
    "2002": [
        "Alkaline Trio",
        "Allister",
        "Andrew W.K.",
        "Anti-Flag",
        "Avenged Sevenfold",
        "Bad Religion",
        "Box Car Racer",
        "Boysetsfire",
        "The Casualties",
        "The Damned",
        "Deviates",
        "District 7",
        "The Early November",
        "Every Time I Die",
        "Finch",
        "Five Iron Frenzy",
        "Flogging Molly",
        "From Autumn to Ashes",
        "The Gilligans",
        "Glassjaw",
        "Gob",
        "Goldfinger",
        "Good Charlotte",
        "Guttermouth",
        "Home Grown",
        "Hope",
        "Hot Water Music",
        "It's Pouring on Our Heads",
        "Jimmy Eat World",
        "The Know How[29]",
        "Lagwagon",
        "Lillix",
        "Luckie Strike",
        "Manic Hispanic",
        "Middleground",
        "MI6",
        "The Mighty Mighty Bosstones",
        "Motion City Soundtrack",
        "The Movielife",
        "MxPx",
        "N.E.R.D",
        "New Found Glory",
        "NOFX",
        "No Use for a Name",
        "Ozma",
        "Quarashi",
        "Reel Big Fish",
        "Rx Bandits",
        "Senses Fail",
        "Simple Plan",
        "Something Corporate",
        "Somerset",
        "The Starting Line",
        "Story of the Year",
        "Switched",
        "Thrice",
        "Thursday",
        "Tiger Army",
        "Trust Company",
        "Tsunami Bomb",
        "The Used",
        "West Beverly",
        "Yellowcard"
    ],
    "2003": [
        "The All-American Rejects",
        "Andrew W.K.",
        "The Arrogant Sons of Bitches",
        "The Ataris",
        "Avenged Sevenfold",
        "Bi-Level",
        "Blackfire",
        "Bleed the Dream",
        "Bowling for Soup",
        "Brand New",
        "Coheed and Cambria",
        "Doozer",
        "Dropkick Murphys",
        "The Early November",
        "Face to Face",
        "Flogging Molly",
        "From Autumn to Ashes",
        "Glassjaw",
        "The Goodwill",
        "Greg Wood",
        "High School Football Heroes",
        "It's Pouring on Our Heads",
        "Jumping Monks",
        "The Know How[29]",
        "Less Than Jake",
        "Mad Caddies",
        "Matchbook Romance",
        "Me First and the Gimme Gimmes",
        "Mestmothe",
        "Midtown",
        "Motion City Soundtrack",
        "No Man's Land",
        "Pennywise",
        "Poison the Well",
        "Rancid",
        "Rev 9",
        "Simple Plan",
        "Something Corporate",
        "The Starting Line",
        "Story of the Year",
        "Suicide Machines",
        "Sum 41",
        "Taking Back Sunday",
        "Thrice",
        "Trashing Andi",
        "Treephort",
        "Tsunami Bomb",
        "Twiztid",
        "Underoath",
        "The Unseen",
        "The Used",
        "Vaux",
        "Vendetta Red",
        "Yellowcard"
    ],
    "2004": [
        "Alkaline Trio",
        "Allister",
        "Amber Pacific",
        "Anti-Flag",
        "The Arrogant Sons of Bitches",
        "Atmosphere",
        "Avenged Sevenfold",
        "A Wilhelm Scream",
        "Bad Religion",
        "Billy Talent",
        "The Bled",
        "Bleed the Dream",
        "Bouncing Souls",
        "Bowling for Soup",
        "The Casualties",
        "Coheed and Cambria",
        "The Early November",
        "Eden Row",
        "Eighteen Visions",
        "Eightyonedays",
        "Fall Out Boy",
        "Fear Before the March of Flames",
        "The Fighting Jacks",
        "The F-Ups",
        "Flogging Molly",
        "From Autumn to Ashes",
        "From First to Last",
        "Go Jimmy Go",
        "Gogol Bordello",
        "Going Second",
        "Good Charlotte",
        "Guttermouth",
        "High School Football Heroes",
        "The (International) Noise Conspiracy",
        "It's Pouring on Our Heads",
        "Jumping Monks",
        "Large Marge",
        "Lars Frederiksen and the Bastards",
        "Letter Kills",
        "Loser's Luck",
        "Mae",
        "The Matches",
        "Moments in Grace",
        "Motion City Soundtrack",
        "My Chemical Romance",
        "New Found Glory",
        "NOFX",
        "No Man's Land",
        "Over It",
        "Pepper",
        "Rise Against",
        "Roses Are Red",
        "Rufio",
        "The Salads",
        "Senses Fail",
        "Shiragirl",
        "Silverstein",
        "Simple Plan",
        "The Sounds",
        "Story of the Year",
        "Stretch Armstrong",
        "Strung Out",
        "Sugarcult",
        "Taking Back Sunday",
        "Thursday",
        "Tiger Army",
        "Underoath",
        "The Used",
        "Valient Thorr",
        "The Vandals",
        "Vaux",
        "Yellowcard",
        "You Win Anyways"
    ],
    "2005": [
        "A Day to Remember",
        "The All-American Rejects",
        "Allister",
        "Amber Pacific",
        "Armor for Sleep",
        "As Tall as Lions",
        "The Ataris",
        "A Thorn for Every Heart",
        "Atmosphere",
        "Atreyu",
        "Avenged Sevenfold",
        "A Wilhelm Scream",
        "Bedouin Soundclash",
        "Big D and the Kids Table",
        "Billy Idol",
        "Billy Talent",
        "The Bled",
        "Bleeding Through",
        "Bleed the Dream",
        "Bowling for Soup",
        "Boys Night Out",
        "Cartel",
        "The Chop Tops",
        "Circa Survive",
        "Darkest Hour",
        "The Dillinger Escape Plan",
        "Dropkick Murphys",
        "Emery",
        "The Fabulous Rudies",
        "The Fall of Troy",
        "Fall Out Boy",
        "The Fight",
        "Final Summation",
        "From First to Last",
        "Funeral for a Friend",
        "Gatsby's American Dream",
        "Going Second",
        "Gratitude",
        "Greeley Estates",
        "Gym Class Heroes",
        "Halifax",
        "Hawthorne Heights",
        "High School Football Heroes",
        "Hit the Lights",
        "Hopesfall",
        "Horrorpops",
        "Immortal Technique",
        "It's Pouring on Our Heads",
        "The Junior Varsity",
        "Kiros",
        "The Know How[29]",
        "The Letters Organize",
        "Loser's Luck",
        "Love Equals Death",
        "Mae",
        "Matchbook Romance",
        "The Matches",
        "Mestmothe",
        "Millencolin",
        "Motion City Soundtrack",
        "MxPx",
        "My American Heart",
        "My Chemical Romance",
        "Near Miss",
        "Nonpoint",
        "No Use for a Name",
        "The Offspring",
        "Oneyedjacks",
        "Over It",
        "Paramore",
        "Plain White T's",
        "Preston",
        "The Receiving End of Sirens",
        "The Red Jumpsuit Apparatus",
        "Reggie and the Full Effect",
        "Relient K",
        "The Riverboat Gamblers",
        "Roger Miret and the Disasters",
        "Roses Are Red",
        "Rufio",
        "The Salads",
        "Saosin",
        "Scary Kids Scaring Kids",
        "Senses Fail",
        "Shiragirl",
        "Silverstein",
        "Simple Plan",
        "Skindred",
        "Sleeper Set Sail",
        "Someday Never",
        "Something Corporate",
        "The Starting Line",
        "Story of the Year",
        "Strike Anywhere",
        "Strung Out",
        "Stutterfly",
        "Suburban Legends",
        "Suicide Machines",
        "Thrice",
        "Tip the Van",
        "Transplants",
        "Tsunami Bomb",
        "Underoath",
        "The Unseen",
        "Urinal Mints",
        "Valient Thorr",
        "The Vanished",
        "Voodoo Blue",
        "You Win Anyways",
        "Zao"
    ],
    "2006": [
        "The Academy Is...",
        "Aiden",
        "Amber Pacific",
        "Amory",
        "Anti-Flag",
        "Armor for Sleep",
        "Bayside",
        "Billy Talent",
        "Blacklist Royals",
        "The Bled",
        "Bleeding Orange",
        "Bouncing Souls",
        "Boysetsfire",
        "Britt Black",
        "Bullet For My Valentine",
        "Cartel",
        "The Casualties",
        "Chiodos",
        "The Chop Tops",
        "Citizen",
        "Die' Hunns",
        "Dr. Madd Vibe",
        "The Early November",
        "Emery",
        "Escape The Fate",
        "Every Time I Die",
        "The Fabulous Rudies",
        "The Flatliners",
        "Florence",
        "From Autumn to Ashes",
        "From First to Last",
        "Gatsby's American Dream",
        "Germs",
        "The Graduate",
        "Greeley Estates",
        "Gym Class Heroes",
        "He Is Legend",
        "Hellogoodbye",
        "Helmet",
        "High School Football Heroes",
        "Hit the Lights",
        "I Am the Avalanche",
        "It's Pouring on Our Heads",
        "Jay Tea",
        "Joan Jett and the Blackhearts",
        "The Johnstones",
        "June",
        "The Junior Varsity",
        "Karate High School",
        "Less Than Jake",
        "The Living End",
        "Love Equals Death",
        "Ludo",
        "Manic Sewing Circle",
        "MewithoutYou",
        "Moneen",
        "Motion City Soundtrack",
        "Motionless in White",
        "Mutemath",
        "The New Sincerity",
        "NOFX",
        "Over It",
        "Paramore",
        "Pathway To Providence",
        "Phathom",
        "The Pink Spiders",
        "Pistolita",
        "Plain White T's",
        "Protest The Hero",
        "Psychotic 4",
        "The Red Jumpsuit Apparatus",
        "Rise Against",
        "The Salads",
        "Saves the Day",
        "Shiragirl",
        "Silverstein",
        "Single File",
        "The Sleeping",
        "The Smashup",
        "So They Say",
        "Someday Never",
        "The Sounds",
        "The Sunstreak",
        "Sydney",
        "Talib Kweli",
        "TAT",
        "Thursday",
        "Tip the Van",
        "Underoath",
        "Valient Thorr",
        "The Vincent Black Shadow",
        "You Win Anyways",
        "Zebrahead"
    ],
    "2007": [
        "Adolescents",
        "Agent Orange",
        "Alesana",
        "Alkaline Trio",
        "All Time Low",
        "The Almost",
        "Amber Pacific",
        "Anberlin",
        "As Cities Burn",
        "As I Lay Dying",
        "The Audition",
        "The Automatic",
        "Avenged Sevenfold",
        "Bad Religion",
        "Bayside",
        "Biffy Clyro",
        "Big D and the Kids Table",
        "Blacklist Royals",
        "Bleed the Dream",
        "Blessthefall",
        "Boys Like Girls",
        "The Briggs",
        "Buck-O-Nine",
        "The Chariot",
        "Chiodos",
        "Cinematic Sunrise",
        "Circa Survive",
        "Circle Jerks",
        "Coheed and Cambria",
        "The Confession",
        "Crowned King",
        "Cute Is What We Aim For",
        "The Dear & Departed",
        "Desperation Squad",
        "The Dickies",
        "Double XL",
        "Drop Dead, Gorgeous",
        "Envy On The Coast",
        "Escape The Fate",
        "Evaline",
        "Evergreen Terrace",
        "The Fabulous Rudies",
        "Family Force 5",
        "Fear",
        "Fishbone",
        "The Flatliners",
        "Flogging Molly",
        "The Fold",
        "Forever The Sickest Kids",
        "Funeral for a Friend",
        "Gallows",
        "Go Crash Audio",
        "The Gufs",
        "Haste the Day",
        "Hawthorne Heights",
        "Hot Rod Circuit",
        "The Human Abstract",
        "I Am Ghost",
        "illScarlett",
        "It Dies Today",
        "The Johnstones",
        "K-os",
        "Kaddisfly",
        "Karate High School",
        "Killswitch Engage",
        "Look What I Did",
        "Ludo",
        "The Maine",
        "Manic Hispanic",
        "Manic Sewing Circle",
        "The Matches",
        "Mayday Parade",
        "Maylene & The Sons Of Disaster",
        "MC Chris",
        "Meg & Dia",
        "Monty are I",
        "Motionless in White",
        "MxPx",
        "My American Heart",
        "New Found Glory",
        "New Years Day",
        "Norma Jean",
        "Nothington",
        "Only Crime",
        "Paramore",
        "Parkway Drive",
        "Pendleton",
        "Pennywise",
        "Pepper",
        "Phathom",
        "The Photo Atlas",
        "Pistolita",
        "PlayRadioPlay",
        "Poison the Well",
        "Protest The Hero",
        "Real McKenzies",
        "The Red Jumpsuit Apparatus",
        "Remsa 'n Event",
        "Revolution Mother",
        "The Rocket Summer",
        "The Salads",
        "Scary Kids Scaring Kids",
        "Secret Broadcast",
        "Set Your Goals",
        "So They Say",
        "The Spill Canvas",
        "The Starting Line",
        "Still Remains",
        "Straylight Run",
        "Street Drum Corps",
        "Sum 41",
        "Supernova",
        "Thirty Seconds to Mars",
        "Throwdown",
        "Throw The Fight",
        "Tiger Army",
        "Title Fight",
        "Total Chaos",
        "The Unseen",
        "The Used",
        "Valencia",
        "The Vandals",
        "The Vincent Black Shadow",
        "weatherPROOF",
        "Yellowcard",
        "You Me Everyone We Know",
        "You Win Anyways"
    ],
    "2008": [
        "The Academy Is...",
        "A Day to Remember",
        "All That Remains",
        "All Time Low",
        "Anarbor",
        "Anberlin",
        "Angels & Airwaves",
        "Animo",
        "Architects",
        "As I Lay Dying",
        "August Burns Red",
        "Authority Zero",
        "Automatic Love Letter",
        "Beat Union",
        "Bedouin Soundclash",
        "Between the Trees",
        "Be Your Own Pet",
        "Big Drill Car",
        "Black President",
        "Blas\u00e9 Debris",
        "The Bleeding Irish",
        "Bouncing Souls",
        "The Briggs",
        "Bring Me The Horizon",
        "Broadway Calls",
        "The Bronx",
        "Buffalo Casket",
        "Casket Architects",
        "Charged GBH",
        "Charlotte Sometimes",
        "Chiodos",
        "Cinder Road",
        "Cinematic Sunrise",
        "Citizen X",
        "The Classic Crime",
        "Cobra Starship",
        "Cold Fusion",
        "The Color Fred",
        "Confide",
        "Crashcarburn",
        "Crime in Stereo",
        "Culture Shock Camp",
        "Danger Radio",
        "Dante",
        "Dead Legend",
        "The Devil Wears Prada",
        "D.I.",
        "The Dickies",
        "The Dillinger Escape Plan",
        "Disco Ensemble",
        "Dodger",
        "Does It Offend You, Yeah?",
        "Dr. Manhattan",
        "Drive A",
        "Edreys",
        "Entice",
        "Every Avenue",
        "Every Time I Die",
        "Fall From Grace",
        "Family Force 5",
        "Farewell",
        "Fear",
        "Fear Nuttin' Band",
        "Fight Fight Fight",
        "The Flatliners",
        "Forever The Sickest Kids",
        "Four Year Strong",
        "From First to Last",
        "Gaslight Anthem",
        "GBH",
        "Germs",
        "Gil Mantera's Party Dream",
        "Greeley Estates",
        "Gym Class Heroes",
        "HiFi Handgrenades",
        "The Higher",
        "Honor Bright",
        "Horrorpops",
        "The Human Abstract",
        "Hunter Revenge",
        "Ivens",
        "Jack's Mannequin",
        "Jeffree Star",
        "Jet Lag Gemini",
        "The Johnstones",
        "Just Surrender",
        "Katy Perry",
        "Last Great Assault",
        "The Lordz",
        "Lost Point",
        "Love Equals Death",
        "Ludo",
        "Madina Lake",
        "The Maine",
        "Marissa Mishelle",
        "Massive Monkees",
        "Matisyahu",
        "Mayday Parade",
        "Maylene & The Sons Of Disaster",
        "MC Chris",
        "Medium Troy",
        "M.I.A.",
        "Middle Finger Salute",
        "Midnight To Twelve",
        "Mike Watt + The Missingmen",
        "Miracle Dolls",
        "Mo Bigsley",
        "Moe Pope",
        "Motion City Soundtrack",
        "Motionless in White",
        "Norma Jean",
        "Now On",
        "Oceana",
        "On The Surface",
        "Ore Ska Band",
        "Othello",
        "Paige Wood",
        "Panima",
        "Paramore",
        "Patent Pending",
        "Pato",
        "Pennywise",
        "Peter DiStefano",
        "Phathom",
        "Pierce the Veil",
        "The Pinker Tones",
        "The Pink Spiders",
        "Piotta",
        "Protest The Hero",
        "Pull The Pin",
        "The Randies",
        "The Recovering",
        "Red Car Wire",
        "Reel Big Fish",
        "Relient K",
        "Revolution Mother",
        "Rise Against",
        "Saint Alvia",
        "Say Anything",
        "Say No More",
        "The Secret Handshake",
        "Senses Fail",
        "Set Your Goals",
        "Settings",
        "Shwayze",
        "Sick City",
        "Single File",
        "Skeet Skeet",
        "Sky Eats Airplane",
        "Staylefish",
        "Stick to Your Guns",
        "Story of the Year",
        "Street Dogs",
        "Street Drum Corps",
        "Supe",
        "TAT",
        "Thrice",
        "Treaty of Paris",
        "T.S.O.L.",
        "Underoath",
        "Valencia",
        "The Vandals",
        "Vanna",
        "We the Kings",
        "You Me Everyone We Know",
        "You Win Anyways"
    ],
    "2009": [
        "Abriel",
        "A Day to Remember",
        "Aiden",
        "All Time Low",
        "Amely",
        "Amplify This",
        "Anarbor",
        "And I've Landed",
        "Anti-Flag",
        "The Ataris",
        "Attack Attack!",
        "Bad Religion",
        "Bayside",
        "Big D and the Kids Table",
        "Big Drill Car",
        "Black Box",
        "Black Tide",
        "Bouncing Souls",
        "Breathe Carolina",
        "Breathe Electric",
        "BrokeNCYDE",
        "Chiodos",
        "Dance Gavin Dance",
        "Dear and the Headlights",
        "The Devil Wears Prada",
        "The Dickies",
        "Emmure",
        "Escape The Fate",
        "Every Avenue",
        "The Flatliners",
        "Flogging Molly",
        "Gallows",
        "Guttermouth",
        "Hello Beautiful",
        "Hit the Lights",
        "I Set My Friends On Fire",
        "In this Moment",
        "InnerPartySystem",
        "Jeffree Star",
        "Jet Lag Gemini",
        "Less Than Jake",
        "Longway",
        "Madina Lake",
        "The Maine",
        "Meg & Dia",
        "Middle Finger Salute",
        "Millionaires",
        "Monty are I",
        "Motion City Soundtrack",
        "NOFX",
        "P.O.S",
        "Paramore",
        "Phathom",
        "Reel Big Fish",
        "Saosin",
        "Saving Grace",
        "Say When",
        "Scary Kids Scaring Kids",
        "Shad",
        "Shooter Jennings",
        "Silverstein",
        "Sing It Loud",
        "Staylefish",
        "Streetlight Manifesto",
        "Sum 41",
        "TAT",
        "Tess Dunn",
        "VersaEmerge",
        "We the Kings",
        "You Me at Six"
    ],
    "2010": [
        "5606",
        "Adolescents",
        "Alkaline Trio",
        "The All-American Rejects",
        "American Sixgun",
        "Anarbor",
        "Andrew W.K.",
        "Angry Samoans",
        "Anti-Flag",
        "April Chase",
        "Artist Vs Poet",
        "Assorted Jelly Beans",
        "Attack Attack!",
        "Automatic Love Letter",
        "Beacher's Madhouse",
        "Big D and the Kids Table",
        "The BOTS",
        "Brass Tackz",
        "Breathe Carolina",
        "Breathe Electric",
        "Bring Me The Horizon",
        "Burning Empires",
        "Call the Cops",
        "Callback California",
        "The Casualties",
        "Chase Long Beach",
        "Closure in Moscow",
        "Columbyne",
        "Confide",
        "The Dickies",
        "The Dillinger Escape Plan",
        "Dropkick Murphys",
        "Emarosa",
        "Emmure",
        "Enter Shikari",
        "Every Time I Die",
        "Eyes Set To Kill",
        "The Fabulous Rudies",
        "Face to Face",
        "Fight Fair",
        "The Flatliners",
        "Forever Came Calling",
        "Forever The Sickest Kids",
        "Hey Monday",
        "I See Stars",
        "ivy league",
        "Iwrestledabearonce",
        "LIGHTS",
        "Mayday Parade",
        "Mike Posner",
        "Motion City Soundtrack",
        "Motionless in White",
        "Never Shout Never",
        "Of Mice & Men",
        "Parkway Drive",
        "Pennywise",
        "Pierce the Veil",
        "The Pretty Reckless",
        "Reel Big Fish",
        "The Rocket Summer",
        "Set Your Goals",
        "Simple Plan",
        "Streetlight Manifesto",
        "Suicide Silence",
        "Sum 41",
        "The Summer Set",
        "Tess Dunn",
        "VersaEmerge",
        "We Are The In Crowd",
        "We the Kings",
        "Whitechapel",
        "The Word Alive",
        "You Me at Six"
    ],
    "2011": [
        "The Acacia Strain",
        "A Day to Remember",
        "AM Taxi",
        "Anti-Flag",
        "Asking Alexandria",
        "Attack Attack!",
        "August Burns Red",
        "Bad Rabbits",
        "Big B",
        "Big Chocolate",
        "Big D and the Kids Table",
        "The Black Pacific",
        "Black Square",
        "Blacklist Royals",
        "Black Veil Brides",
        "Blood on the Dance Floor",
        "The BOTS",
        "Bowling for Soup",
        "Brothers Of Brazil",
        "Campaigning For Zeros",
        "Cold Forty Three",
        "Columbyne",
        "Continental",
        "Dance Gavin Dance",
        "The Dance Party",
        "The Dangerous Summer",
        "DC Fallout",
        "Dead Cat Lounge",
        "Demerit",
        "The Devil Wears Prada",
        "D.R.U.G.S.",
        "Electric Touch",
        "Enter Shikari",
        "Evelynn",
        "Every Avenue",
        "The Expendables",
        "The Exposed",
        "Eyes Set To Kill",
        "Falling In Reverse",
        "Family Force 5",
        "The Fold",
        "Forget Me In Vegas",
        "Foxy Shazam",
        "Freshman 15",
        "Gatsby's American Dream",
        "Go Radio",
        "Good Guys In Black",
        "Grieves with Budo",
        "Gym Class Heroes",
        "Hellogoodbye",
        "I Set My Friends On Fire",
        "illScarlett",
        "It Boys!",
        "Jack's Mannequin",
        "Larry And His Flask",
        "Less Than Jake",
        "Lionize",
        "Lucero",
        "Machree",
        "Madina Lake",
        "MC Lars with Weerd Science",
        "The Menzingers",
        "Middle Class Rut",
        "Miss May I",
        "Mojo Morgan",
        "Motionless in White",
        "Moving Mountains",
        "My Arcadia",
        "The Narrative",
        "Neo Geo",
        "New Years Day",
        "Of Mice & Men",
        "Paramore",
        "Passafire",
        "Peelander-Z",
        "Pepper",
        "Permanent Bastards",
        "Places And Numbers",
        "Planet Smashers",
        "Pour Habit",
        "Railroad To Alaska",
        "Rapid Decline",
        "The Ready Set",
        "Relient K",
        "River City Extension",
        "Set Your Goals",
        "Sharks",
        "The Sheds",
        "Shinobi Ninja",
        "Shira",
        "Shut Up And Deal",
        "Sick of Sarah",
        "Simple Plan",
        "So Long Arletta",
        "Stephen Jerzak",
        "Street Dogs",
        "The Suit",
        "Sum 41",
        "Terrible Things",
        "Tess Dunn",
        "There For Tomorrow",
        "Tomorrow's Bad Seeds",
        "Tornado Rider",
        "Unwritten Law",
        "Veara",
        "Vonnegutt",
        "We Came As Romans",
        "Weerd Science",
        "We're Doomed",
        "Winds Of Plague",
        "Windsor Drive",
        "Woe, Is Me",
        "The Wonder Years",
        "The Word Alive",
        "Yelawolf"
    ],
    "2012": [
        "After the Burial",
        "All Time Low",
        "Amyst",
        "Anthony Raneri of Bayside",
        "Anti-Flag",
        "August Burns Red",
        "Ballyhoo!",
        "Bangups",
        "Bayside",
        "Blessthefall",
        "Blood on the Dance Floor",
        "Born of Osiris",
        "Breathe Carolina",
        "Brian Marquis",
        "Captain Capa",
        "CatchingYourClouds",
        "Champagne Champagne",
        "Chelsea Grin",
        "Cherri Bomb",
        "Chiodos",
        "Chuck Ragan of Hot Water Music",
        "Chunk! No, Captain Chunk",
        "Cold Forty Three",
        "The Constellations",
        "Danielle Barbe",
        "The Darlings",
        "Dead Sara",
        "Divided By Friday",
        "Dustin Jones and the Rising Tide",
        "Echo Movement",
        "Emily's Army",
        "Every Time I Die",
        "Falling In Reverse",
        "Fireworks",
        "For Today",
        "Four Year Strong",
        "Funeral Party",
        "G-Eazy",
        "The Ghost Inside",
        "The Green",
        "Hostage Calm",
        "Hyro Da Hero",
        "I Am the Avalanche",
        "I Call Fives",
        "I Fight Dragons",
        "Impending Doom",
        "Into It. Over It.",
        "Ionia",
        "It Boys!",
        "Iwrestledabearonce",
        "The Jukebox Romantics",
        "June Divided",
        "Justina",
        "Koji",
        "Living With Lions",
        "Lost In Society",
        "Lostprophets",
        "Machine Gun Kelly",
        "Make Do and Mend",
        "Man Overboard",
        "Matt Toka",
        "Mayday Parade",
        "MC Lars with Weerd Science",
        "Memphis May Fire",
        "Mighty Mongo",
        "Miss May I",
        "Mod Sun",
        "Motionless in White",
        "Neo Geo",
        "New Found Glory",
        "Of Mice & Men",
        "Oh No Fiasco",
        "Owen Plant",
        "Pierce the Veil",
        "Polar Bear Club",
        "Rise Against",
        "Rise To Remain",
        "The Scissors",
        "Senses Fail",
        "Sick of Sarah",
        "The Silver Comet",
        "Silverstein",
        "Simple Plan",
        "Skinny Lister",
        "Skip The Foreplay",
        "Sleeping With Sirens",
        "Sleepwalker",
        "Stepdad",
        "Streetlight Manifesto",
        "Super Water Sympathy",
        "T. Mills",
        "Taking Back Sunday",
        "Taylor Thrash",
        "Ten Second Epic",
        "Tess Dunn",
        "They All Float",
        "Title Fight",
        "Tomorrow's Bad Seeds",
        "Tonight Alive",
        "Tony D'Angelo",
        "Transit",
        "Twin Atlantic",
        "The Used",
        "Vampires Everywhere!",
        "Vanna",
        "We Are The In Crowd",
        "We Are The Ocean",
        "We the Kings",
        "Wick-It The Instigator",
        "Yellowcard",
        "You Me at Six",
        "Young London"
    ],
    "2013": [
        "Allstar Weekend",
        "Alvarez Kings",
        "The Amity Affliction",
        "Anarbor",
        "The Aquabats",
        "Architects",
        "The Ataris",
        "Attila",
        "August Burns Red",
        "Bangups",
        "Beautiful Bodies",
        "Beebs and Her Money Makers",
        "Beware Of Darkness",
        "Big Chocolate",
        "Big D and the Kids Table",
        "Billy Talent",
        "The Black Dahlia Murder",
        "Black Veil Brides",
        "Blessthefall",
        "Bowling for Soup",
        "Brian Marquis",
        "Bring Me The Horizon",
        "The Chariot",
        "Chase Walker Band",
        "Chiodos",
        "Citizen",
        "TheCityShakeUp",
        "The Cleopatra Complex",
        "Courage My Love",
        "Crizzly",
        "Crossfaith",
        "Crown the Empire",
        "Defeater",
        "Driver Friendly",
        "Dose Of Adolescence",
        "The Early November",
        "Echosmith",
        "Emily's Army",
        "The Exposed",
        "Five Knives",
        "For The Foxes",
        "Forever Came Calling",
        "Forever The Sickest Kids",
        "Gabe Kubanda",
        "Gin Wigmore",
        "Go Radio",
        "Goldfinger",
        "Goldhouse",
        "Greek Fire",
        "Handguns",
        "Hands Like Houses",
        "Hawthorne Heights",
        "Heritage",
        "I See Stars",
        "Ice Nine Kills",
        "The Indecent",
        "Issues",
        "Itch",
        "Juliet Simms",
        "Kairo Kingdom",
        "Like Moths to Flames",
        "Lionz of Zion",
        "Lost In Atlantis",
        "Mac Lethal",
        "Madchild",
        "Man Overboard",
        "MC Lars",
        "Memphis May Fire",
        "Mestmothe",
        "Middle Finger Salute",
        "Mighty Mongo",
        "Mixtapes",
        "Motion City Soundtrack",
        "Never Shout Never",
        "New Beat Fund",
        "New Empire",
        "New Years Day",
        "No Bragging Rights",
        "Oh, Sleeper",
        "Outasight",
        "Pacific Dub",
        "Psycho White",
        "PVRIS",
        "RDGLDGRN",
        "Real Friends",
        "Reel Big Fish",
        "Relient K",
        "Run DMT",
        "Ryan Cassata",
        "SECRETS",
        "Set It Off",
        "Shy KidX",
        "Silverstein",
        "Sleeping With Sirens",
        "Stephan Jacobs",
        "Stick to Your Guns",
        "Story of the Year",
        "The Story So Far",
        "Strawberry Blondes",
        "The Summer Set",
        "Super Water Sympathy",
        "The Swellers",
        "Tess Dunn",
        "Texas in July",
        "Tonight Alive",
        "Upon a Burning Body",
        "The Used",
        "VersaEmerge",
        "Volumes",
        "Wallpaper.",
        "Waterparks",
        "We Came As Romans",
        "While She Sleeps",
        "Woe, Is Me",
        "The Wonder Years",
        "Young London"
    ],
    "2014": [
        "Aaron West and the Roaring Twenties",
        "A Day to Remember",
        "American Pinup",
        "Anberlin",
        "Anthony Raneri of Bayside",
        "Antiserum",
        "The Ataris",
        "Attila",
        "Bad Rabbits",
        "Beartooth",
        "Beebs and Her Money Makers",
        "Born of Osiris",
        "Bowling for Soup",
        "Breathe Carolina",
        "Captain Capa",
        "Chase Walker Band",
        "Chelsea Grin",
        "Chunk! No, Captain Chunk",
        "TheCityShakeUp",
        "Close Your Eyes",
        "The Color Morale",
        "Courage My Love",
        "Crizzly",
        "Crown the Empire",
        "Cursed Sails",
        "Cute Is What We Aim For",
        "Dangerkids",
        "The Devil Wears Prada",
        "DJ Nicola Bear",
        "DJ Scout",
        "Echosmith",
        "Emilie Autumn",
        "Enter Shikari",
        "Every Time I Die",
        "Face The King",
        "Falling In Reverse",
        "Falling Through April",
        "Finch",
        "Fit For a King",
        "For All Those Sleeping",
        "For Today",
        "Four Year Strong",
        "Get Scared",
        "The Ghost Inside",
        "Ghost Town",
        "Heart To Heart",
        "I Fight Dragons",
        "I, the Breather",
        "I the Mighty",
        "Ice Nine Kills",
        "Icon For Hire",
        "Issues",
        "K.Flay",
        "Less Than Jake",
        "Life on the Sideline",
        "Linkin Park",
        "Lionize",
        "The Lost Boys",
        "Lost In Society",
        "The Maine",
        "Marmozets",
        "Mayday Parade",
        "MC Chris",
        "Me Like Bees",
        "Mixtapes",
        "Mod Sun",
        "Motionless in White",
        "Naked Walrus",
        "Neck Deep",
        "NiT GriT",
        "Of Mice & Men",
        "One Ok Rock",
        "Pacific Dub",
        "Parkway Drive",
        "Plague Vendor",
        "The Protomen",
        "PVRIS",
        "The Ready Set",
        "Real Friends",
        "Saves the Day",
        "Scare Don't Fear",
        "SECRETS",
        "Shinobi Ninja",
        "Shot In The Dark",
        "Sleeper Agent",
        "Sleeping With Sirens",
        "State Champs",
        "The Story So Far",
        "Strangers You Know",
        "Stray from the Path",
        "The Summer Set",
        "Survive This!",
        "Teenage Bottlerocket",
        "Terror",
        "Tess Dunn",
        "This Wild Life",
        "To The Wind",
        "Unlocking The Truth",
        "Vanna",
        "Volumes",
        "Watsky",
        "Wax",
        "We Are The In Crowd",
        "We the Kings",
        "Wind In Sails",
        "The Word Alive",
        "Yellowcard"
    ],
    "2015": [
        "'68",
        "A+ Dropouts",
        "Aaron West and the Roaring Twenties",
        "Alive Like Me",
        "Alvarez Kings",
        "American Opera",
        "The Amity Affliction",
        "Ascot Royals",
        "As It Is",
        "Asking Alexandria",
        "Attila",
        "August Burns Red",
        "Baby Baby",
        "Bad Cop / Bad Cop",
        "Beartooth",
        "Beautiful Bodies",
        "Bebe Rexha",
        "Being As An Ocean",
        "Black Boots",
        "Black Veil Brides",
        "Blessthefall",
        "Born Cages",
        "BoyMeetsWorld",
        "Brian Marquis",
        "The Bunny The Bear",
        "Buttons",
        "Candy Hearts",
        "Carousel Kings",
        "ChrisB",
        "Citizen",
        "Corrin Campbell",
        "Crossfaith",
        "The Dirty Nil",
        "Drama Club",
        "Eli Olsberg",
        "Emarosa",
        "Escape The Fate",
        "Falling Through April",
        "False Puppet",
        "Family Force 5",
        "Fit For a King",
        "Four Year Strong",
        "Grey Gordon",
        "Handguns",
        "Hands Like Houses",
        "Have Mercy",
        "H2O",
        "Hundredth",
        "I Killed The Prom Queen",
        "Icon For Hire",
        "Insomniac",
        "Isles",
        "James Morris",
        "Jule Vera",
        "Juliet Simms",
        "The Karma Killers",
        "Kaya Stewart",
        "The Kenneths",
        "Knuckle Puck",
        "Koji",
        "Koo Koo Kanga Roo",
        "Kosha Dillz",
        "Le Castle Vania",
        "Lee Corey Oswald",
        "M4Sonic",
        "Macy Kate",
        "Major League",
        "Mallory Knox",
        "Man Overboard",
        "Matchbook Romance",
        "MC Lars",
        "Meghann Wright",
        "Memphis May Fire",
        "Metro Station",
        "Miss May I",
        "Mod Sun",
        "Moose Blood",
        "Motion City Soundtrack",
        "Neck Deep",
        "Never Shout Never",
        "New Beat Fund",
        "New Years Day",
        "Night Argent",
        "Night Riots",
        "Onward, Etc.",
        "Our Last Night",
        "Pierce the Veil",
        "PVRIS",
        "SayWeCanFly",
        "Seaway",
        "Senses Fail",
        "Set It Off",
        "Set Your Goals",
        "Shiragirl",
        "Silverstein",
        "Simple Plan",
        "Sleeping With Sirens",
        "Stacked Like Pancakes",
        "Strangers You Know",
        "TAT",
        "Tess Dunn",
        "This Wild Life",
        "Transit",
        "Trophy Eyes",
        "Waterparks",
        "We Came As Romans",
        "While She Sleeps",
        "The Wonder Years"
    ],
    "2016": [
        "3OH!3",
        "Against the Current",
        "American Authors",
        "Assuming We Survive",
        "Atreyu",
        "Avion Roe",
        "Bad Seed Rising",
        "The Ballroom Charades",
        "Ballyhoo!",
        "Broadside",
        "Bullet For My Valentine",
        "Cane Hill",
        "Capsize",
        "Chelsea Grin",
        "Chunk! No, Captain Chunk",
        "Coldrain",
        "The Color Morale",
        "Crown the Empire",
        "Cruel Hand",
        "Dash | Ten",
        "Emarosa",
        "Enough Already",
        "Every Time I Die",
        "Falling In Reverse",
        "First To Eleven",
        "Four Year Strong",
        "From Ashes To New",
        "Ghost Town",
        "Gideon",
        "Good Charlotte",
        "Hail the Sun",
        "The Heirs",
        "I See Stars",
        "Ice Nine Kills",
        "In Hearts Awake",
        "The Interrupters",
        "Issues",
        "Knuckle Puck",
        "Less Than Jake",
        "Like Pacific",
        "The Maine",
        "Marina City",
        "Masked Intruder",
        "Mayday Parade",
        "More To Monroe",
        "Mother Feather",
        "Motionless in White",
        "Neck Deep",
        "New Found Glory",
        "The New Low",
        "Night Argent",
        "Oceans Ate Alaska",
        "Old Wounds",
        "Palaye Royale",
        "Pepper",
        "The Pink Slips",
        "Prof",
        "PVRIS",
        "Real Friends",
        "Reckless Serenade",
        "Reel Big Fish",
        "Roam",
        "Safe To Say",
        "SayWeCanFly",
        "SECRETS",
        "Set It Off",
        "Set Your Goals",
        "Silent Planet",
        "Sleeping With Sirens",
        "State Champs",
        "The Story So Far",
        "Sum 41",
        "The Summer Set",
        "Sykes",
        "Teenage Bottlerocket",
        "Tonight Alive",
        "Too Close to Touch",
        "Tsunami Bomb",
        "Vanna",
        "Veil Of Maya",
        "Volumes",
        "Wage War",
        "Waka Flocka Flame",
        "Waterparks",
        "We the Kings",
        "Whitechapel",
        "With Confidence",
        "The Word Alive",
        "Yellowcard",
        "Young Guns"
    ],
    "2017": [
        "The Acacia Strain",
        "Adolescents",
        "After the Burial",
        "The Alarm",
        "Alestorm",
        "American Authors",
        "Andy Black",
        "Anti-Flag",
        "The Ataris",
        "Attila",
        "Bad Cop / Bad Cop",
        "Bad Omens",
        "Bad Seed Rising",
        "Barb Wire Dolls",
        "Beartooth",
        "Being As An Ocean",
        "Big D and the Kids Table",
        "Blessthefall",
        "Boston Manor",
        "Bowling for Soup",
        "Candiria",
        "Carnifex",
        "Carousel Kings",
        "CKY",
        "Counterparts",
        "Courage My Love",
        "Creeper",
        "Dance Gavin Dance",
        "The Dickies",
        "Doll Skin",
        "The Dukes",
        "Emmure",
        "Eternal Boy",
        "Falling In Reverse",
        "The Fantastic Plastics",
        "Farewell Winters",
        "Feeki",
        "Fire From The Gods",
        "Fit For a King",
        "Futuristic",
        "Goldfinger",
        "The Gospel Youth",
        "Gwar",
        "Hands Like Houses",
        "Hatebreed",
        "Hawthorne Heights",
        "Hundredth",
        "I Prevail",
        "Jule Vera",
        "Knocked Loose",
        "Memphis May Fire",
        "Microwave",
        "Montage",
        "Movements",
        "Municipal Waste",
        "Naked Walrus",
        "Neck Deep",
        "Never Shout Never",
        "New Years Day",
        "One Last Shot",
        "Our Last Night",
        "Playboy Manbaby",
        "The Riverboat Gamblers",
        "Sammy Adams",
        "Sarah and the Safe Word",
        "Save Ferris",
        "Separations",
        "Shattered Sun",
        "Sick of It All",
        "Silent Planet",
        "Silverstein",
        "Sonic Boom Six",
        "Stacked Like Pancakes",
        "Stick to Your Guns",
        "Street Dogs",
        "Streetlight Manifesto",
        "Strung Out",
        "Suicide Machines",
        "Sworn In",
        "Sylar",
        "Tillie",
        "Too Close to Touch",
        "Trophy Eyes",
        "T.S.O.L.",
        "Twilight Creeps",
        "Valient Thorr",
        "War on Women",
        "Watsky",
        "The Waves",
        "The White Noise",
        "William Control"
    ]
}